jupyterlab_monitor/_version.py
jupyterlab_monitor-1.0.3.data/data/share/jupyter/labextensions/jupyterlab-pioneer/install.json
jupyterlab_monitor-1.0.3.dist-info/METADATA
jupyterlab_monitor-1.0.3.dist-info/WHEEL
jupyterlab_monitor-1.0.3.dist-info/licenses/LICENSE
jupyterlab_monitor-1.0.3.dist-info/RECORD
